{
    "site": {
        "title": "COMCY",
        "description": "Describes the site",
        "favicon": "fav.ico",
        "author": "comcy",
        "year": "2018",
        "logo": "",
        "baseHref": "/",
        "homelabel": "Home"
    },
    "build": {
        "srcPath": "./profile",
        "srcPathSites": "sites",
        "distPath": "./publish",
        "supportedContentExtensionsPattern": "md|ejs|html",
        "srcCustomPathLayouts": "/views/layouts",
        "srcCustomAssets": ""
    }
}